read_structure_step/__init__.py
read_structure_step/_version.py
read_structure_step/errors.py
read_structure_step/read.py
read_structure_step/read_structure.py
read_structure_step/read_structure_parameters.py
read_structure_step/read_structure_step.py
read_structure_step/tk_read_structure.py
read_structure_step/tk_write_structure.py
read_structure_step/utils.py
read_structure_step/write.py
read_structure_step/write_structure.py
read_structure_step/write_structure_parameters.py
read_structure_step/write_structure_step.py
read_structure_step/data/references.bib
read_structure_step/formats/__init__.py
read_structure_step/formats/registries.py
read_structure_step/formats/which.py
read_structure_step/formats/cif/__init__.py
read_structure_step/formats/cif/cif.py
read_structure_step/formats/cif/mmcif.py
read_structure_step/formats/extxyz/__init__.py
read_structure_step/formats/extxyz/extxyz.py
read_structure_step/formats/mol2/__init__.py
read_structure_step/formats/mol2/mol2.py
read_structure_step/formats/mop/__init__.py
read_structure_step/formats/mop/find_mopac.py
read_structure_step/formats/mop/obabel.py
read_structure_step/formats/openbabel_io/__init__.py
read_structure_step/formats/openbabel_io/checkers.py
read_structure_step/formats/openbabel_io/obabel.py
read_structure_step/formats/sdf/__init__.py
read_structure_step/formats/sdf/sdf.py
read_structure_step/formats/smi/__init__.py
read_structure_step/formats/smi/smi.py
read_structure_step/formats/xyz/__init__.py
read_structure_step/formats/xyz/xyz.py
read_structure_step-2026.1.6.dist-info/licenses/AUTHORS.rst
read_structure_step-2026.1.6.dist-info/licenses/LICENSE
tests/__init__.py
tests/build_filenames.py
tests/methylidyne.mop
tests/mopac_exists.py
tests/test_cif.py
tests/test_formats.py
tests/test_read_structure_step.py
tests/test_utils.py
tests/data/3TR_model.json
tests/data/3TR_model.mol2
tests/data/3TR_model.pdb
tests/data/3TR_model.sdf
tests/data/3TR_model.sdf.bz2
tests/data/3TR_model.sdf.gz
tests/data/3TR_model.xyz
tests/data/3TR_model_MN.xyz
tests/data/ABENEB01.cif
tests/data/Cr_ACETCR.mop
read_structure_step-2026.1.6.dist-info/METADATA
read_structure_step-2026.1.6.dist-info/WHEEL
read_structure_step-2026.1.6.dist-info/entry_points.txt
read_structure_step-2026.1.6.dist-info/top_level.txt
read_structure_step-2026.1.6.dist-info/zip-safe
read_structure_step-2026.1.6.dist-info/RECORD
