Metadata-Version: 2.4
Name: read_structure_step
Version: 2026.1.6
Summary: A SEAMM plug-in to read common formats in computational chemistry
Home-page: https://github.com/molssi-seamm/read_structure_step
Author: Eliseo Marin-R-Rimoldi
Author-email: meliseo@vt.edu
License: BSD-3-Clause
Keywords: SEAMM,plug-in,flowchart,Open Babel,molecules,atomistic,files
Platform: Linux
Platform: Mac OS-X
Platform: Unix
Platform: Windows
Classifier: Development Status :: 5 - Production/Stable
Classifier: Intended Audience :: Science/Research
Classifier: Topic :: Scientific/Engineering :: Chemistry
Classifier: Topic :: Scientific/Engineering :: Physics
Classifier: License :: OSI Approved :: BSD License
Classifier: Natural Language :: English
Classifier: Programming Language :: Python :: 3 :: Only
Classifier: Programming Language :: Python :: 3.8
Classifier: Programming Language :: Python :: 3.9
License-File: LICENSE
License-File: AUTHORS.rst
Requires-Dist: seamm
Dynamic: author
Dynamic: author-email
Dynamic: classifier
Dynamic: description
Dynamic: description-content-type
Dynamic: home-page
Dynamic: keywords
Dynamic: license
Dynamic: license-file
Dynamic: platform
Dynamic: requires-dist
Dynamic: summary
